odoo/addons/base_maintenance_config/README.rst
odoo/addons/base_maintenance_config/__init__.py
odoo/addons/base_maintenance_config/__manifest__.py
odoo/addons/base_maintenance_config/i18n/base_maintenance_config.pot
odoo/addons/base_maintenance_config/i18n/es.po
odoo/addons/base_maintenance_config/i18n/it.po
odoo/addons/base_maintenance_config/readme/CONFIGURE.rst
odoo/addons/base_maintenance_config/readme/CONTRIBUTORS.rst
odoo/addons/base_maintenance_config/readme/DESCRIPTION.rst
odoo/addons/base_maintenance_config/readme/USAGE.rst
odoo/addons/base_maintenance_config/static/description/icon.png
odoo/addons/base_maintenance_config/static/description/index.html
odoo/addons/base_maintenance_config/views/res_config_settings.xml
odoo11_addon_base_maintenance_config-11.0.1.0.0.99.dev7.dist-info/METADATA
odoo11_addon_base_maintenance_config-11.0.1.0.0.99.dev7.dist-info/WHEEL
odoo11_addon_base_maintenance_config-11.0.1.0.0.99.dev7.dist-info/top_level.txt
odoo11_addon_base_maintenance_config-11.0.1.0.0.99.dev7.dist-info/RECORD
